setup.py
pybkick/__init__.py
pybkick/kick.py
pybkick/pyboard.py
pybkick.egg-info/PKG-INFO
pybkick.egg-info/SOURCES.txt
pybkick.egg-info/dependency_links.txt
pybkick.egg-info/entry_points.txt
pybkick.egg-info/requires.txt
pybkick.egg-info/top_level.txt
pybkick.egg-info/zip-safe
pybkick_tests/__init__.py
pybkick_tests/test_kick.py
pybkick_tests/test_meta.py
pybkick_tests/test_remote_operations.py