Metadata-Version: 1.1
Name: pybkick
Version: 0.0.2
Summary: Python tools for pushing code onto a PyBoard.
Home-page: https://github.com/salimfadhley/pybkick
Author: Salim Fadhley
Author-email: salimfadhley@gmail.com
License: MIT
Platform: UNKNOWN
Classifier: Development Status :: 4 - Beta
Classifier: Environment :: Console
Classifier: Intended Audience :: Developers
Classifier: License :: OSI Approved :: MIT License
Classifier: Natural Language :: English
Classifier: Operating System :: OS Independent
Classifier: Programming Language :: Python :: 2.7
Classifier: Topic :: Software Development :: Testing
